multipackage/__init__.py
multipackage/exceptions.py
multipackage/manifest.py
multipackage/repo.py
multipackage/data/__init__.py
multipackage/data/scripts/__init__.py
multipackage/data/scripts/better_apidocs.py
multipackage/data/scripts/generate_api.py
multipackage/data/scripts/release_component.py
multipackage/data/scripts/release_notes.py
multipackage/data/scripts/shared_errors.py
multipackage/data/templates/api.rst.tpl
multipackage/data/templates/build_documentation.py.tpl
multipackage/data/templates/components.py.tpl
multipackage/data/templates/components.txt
multipackage/data/templates/conf.py.tpl
multipackage/data/templates/editorconfig
multipackage/data/templates/index.rst.tpl
multipackage/data/templates/module.rst
multipackage/data/templates/package.rst
multipackage/data/templates/pylintrc
multipackage/data/templates/pypi_doctor_template.tpl
multipackage/data/templates/pypi_info_template.tpl
multipackage/data/templates/release.rst.tpl
multipackage/data/templates/release_by_name.py.tpl
multipackage/data/templates/tag_release.py.tpl
multipackage/data/templates/test_by_name.py.tpl
multipackage/data/templates/travis.yml.tpl
multipackage/external/__init__.py
multipackage/external/travis.py
multipackage/scripts/__init__.py
multipackage/scripts/multipackage.py
multipackage/subsystems/__init__.py
multipackage/subsystems/basic.py
multipackage/subsystems/pylint.py
multipackage/subsystems/sphinx.py
multipackage/subsystems/travis.py
multipackage/templates/__init__.py
multipackage/templates/pypi_package.py
multipackage/templates/repo_template.py
multipackage/utilities/__init__.py
multipackage/utilities/file_ops.py
multipackage/utilities/git.py
multipackage/utilities/managed_section.py
multipackage/utilities/obj_hash.py
multipackage/utilities/packages.py
multipackage/utilities/template.py
multipackage-0.2.1.dist-info/LICENSE.md
multipackage-0.2.1.dist-info/METADATA
multipackage-0.2.1.dist-info/WHEEL
multipackage-0.2.1.dist-info/entry_points.txt
multipackage-0.2.1.dist-info/top_level.txt
multipackage-0.2.1.dist-info/RECORD
